examples/__init__.py
examples/ping_client_requests.py
examples/ping_client_thrift.py
examples/ping_server_tornado.py
thriftrw/__init__.py
thriftrw/_buffer.cpython-311-darwin.so
thriftrw/_cython.cpython-311-darwin.so
thriftrw/_runtime.cpython-311-darwin.so
thriftrw/errors.py
thriftrw/loader.py
thriftrw/compile/__init__.py
thriftrw/compile/compiler.py
thriftrw/compile/generate.py
thriftrw/compile/link.py
thriftrw/compile/scope.py
thriftrw/idl/__init__.py
thriftrw/idl/ast.py
thriftrw/idl/lexer.py
thriftrw/idl/parser.py
thriftrw/protocol/__init__.py
thriftrw/protocol/binary.cpython-311-darwin.so
thriftrw/protocol/core.cpython-311-darwin.so
thriftrw/spec/__init__.py
thriftrw/spec/base.cpython-311-darwin.so
thriftrw/spec/check.cpython-311-darwin.so
thriftrw/spec/common.cpython-311-darwin.so
thriftrw/spec/const.py
thriftrw/spec/enum.cpython-311-darwin.so
thriftrw/spec/exc.cpython-311-darwin.so
thriftrw/spec/field.cpython-311-darwin.so
thriftrw/spec/list.cpython-311-darwin.so
thriftrw/spec/map.cpython-311-darwin.so
thriftrw/spec/primitive.cpython-311-darwin.so
thriftrw/spec/reference.cpython-311-darwin.so
thriftrw/spec/service.cpython-311-darwin.so
thriftrw/spec/set.cpython-311-darwin.so
thriftrw/spec/spec_mapper.cpython-311-darwin.so
thriftrw/spec/struct.cpython-311-darwin.so
thriftrw/spec/typedef.cpython-311-darwin.so
thriftrw/spec/union.cpython-311-darwin.so
thriftrw/wire/__init__.py
thriftrw/wire/message.cpython-311-darwin.so
thriftrw/wire/mtype.cpython-311-darwin.so
thriftrw/wire/ttype.cpython-311-darwin.so
thriftrw/wire/value.cpython-311-darwin.so
thriftrw-1.9.0.dist-info/LICENSE
thriftrw-1.9.0.dist-info/METADATA
thriftrw-1.9.0.dist-info/WHEEL
thriftrw-1.9.0.dist-info/top_level.txt
thriftrw-1.9.0.dist-info/RECORD
