Metadata-Version: 2.1
Name: thriftrw
Version: 1.9.0
Summary: A library to serialize and deserialize Thrift values.
Home-page: https://github.com/thriftrw/thriftrw-python
Author: Abhinav Gupta
Author-email: abg@uber.com
License: MIT
Classifier: Development Status :: 5 - Production/Stable
Classifier: Intended Audience :: Developers
Classifier: License :: OSI Approved :: MIT License
Classifier: Programming Language :: Python :: 3
Classifier: Topic :: Software Development :: Libraries :: Python Modules
License-File: LICENSE
Requires-Dist: ply
